webpocket
