Metadata-Version: 1.0
Name: WebPocket
Version: 0.1.2
Summary: Actor-model based WebSocket client in Python
Home-page: https://github.com/xhs/WebPocket/
Author: xhs
Author-email: chef@dark.kitchen
License: BSD
Platform: any
